{
  "data": {
    "ticker": "HTLD",
    "fetch_date": "2026-04-24T14:24:31.141563",
    "quarterly_revenue": {
      "2024-12-31 00:00:00": 242576000.0,
      "2025-03-31 00:00:00": 219420000.0,
      "2025-06-30 00:00:00": 210387000.0,
      "2025-09-30 00:00:00": 196547000.0,
      "2025-12-31 00:00:00": 179355000.0
    },
    "revenue_qoq_change": -8.747017252870815,
    "revenue_yoy_change": -26.062347470483477,
    "quarterly_eps": {
      "2024-12-31 00:00:00": -0.02,
      "2025-03-31 00:00:00": -0.18,
      "2025-06-30 00:00:00": -0.14,
      "2025-09-30 00:00:00": -0.11,
      "2025-12-31 00:00:00": -0.25
    },
    "eps_qoq_change": -127.2727272727273,
    "eps_yoy_change": -1150.0,
    "gross_margin": 9.14,
    "margin_change": -0.43,
    "operating_margin": -8.95,
    "inventory_breakdown_available": false
  },
  "fetched_at": "2026-04-24T14:24:31.142737"
}